regius/__init__.py
regius/callbacks.py
regius/core.py
regius/metrics.py
regius/version.py
regius/tabular/__init__.py
regius/tabular/data.py
regius/tabular/learner.py
regius/tabular/models.py
regius/tabular/preprocessing.py
regius/tabular/utils.py
regius_dl-0.0.7.dist-info/LICENSE
regius_dl-0.0.7.dist-info/METADATA
regius_dl-0.0.7.dist-info/WHEEL
regius_dl-0.0.7.dist-info/top_level.txt
regius_dl-0.0.7.dist-info/RECORD
