Metadata-Version: 2.1
Name: regius-dl
Version: 0.0.7
Summary: Regius Deep Learning Toolbox
Home-page: https://github.com/RegiusQuant/regius
Author: Jiang Yize
Author-email: 315135833@qq.com
License: Apache Software License 2.0
Keywords: deep learning,machine learning
Platform: UNKNOWN
Classifier: Development Status :: 1 - Planning
Classifier: License :: OSI Approved :: Apache Software License
Classifier: Natural Language :: Chinese (Simplified)
Classifier: Programming Language :: Python :: 3.7
Requires-Dist: numpy
Requires-Dist: pandas
Requires-Dist: scikit-learn
Requires-Dist: torch
